{
  "items": [
    {
      "type": "file",
      "path": "BBG4E/BG4E 規劃.canvas",
      "ctime": 1683079389499
    },
    {
      "type": "file",
      "path": "Syntax/Syntax.md",
      "ctime": 1683079389499
    },
    {
      "type": "file",
      "path": "Phrasing-Signs.md",
      "ctime": 1683079389499
    },
    {
      "type": "file",
      "path": "README.md",
      "ctime": 1683079389499
    },
    {
      "type": "file",
      "path": "Idioms.md",
      "ctime": 1683079389499
    },
    {
      "type": "file",
      "path": "Syntax/§311a.md",
      "ctime": 1683079389499
    }
  ]
}